pyramid_jinja2/__init__.py
pyramid_jinja2/configure.zcml
pyramid_jinja2/filters.py
pyramid_jinja2/i18n.py
pyramid_jinja2/settings.py
pyramid_jinja2/scaffolds/__init__.py
pyramid_jinja2/scaffolds/jinja2_starter/+dot+coveragerc_tmpl
pyramid_jinja2/scaffolds/jinja2_starter/CHANGES.rst_tmpl
pyramid_jinja2/scaffolds/jinja2_starter/MANIFEST.in_tmpl
pyramid_jinja2/scaffolds/jinja2_starter/README.rst_tmpl
pyramid_jinja2/scaffolds/jinja2_starter/development.ini_tmpl
pyramid_jinja2/scaffolds/jinja2_starter/message-extraction.ini
pyramid_jinja2/scaffolds/jinja2_starter/pytest.ini_tmpl
pyramid_jinja2/scaffolds/jinja2_starter/setup.cfg_tmpl
pyramid_jinja2/scaffolds/jinja2_starter/setup.py_tmpl
pyramid_jinja2/scaffolds/jinja2_starter/+package+/__init__.py_tmpl
pyramid_jinja2/scaffolds/jinja2_starter/+package+/resources.py
pyramid_jinja2/scaffolds/jinja2_starter/+package+/tests.py_tmpl
pyramid_jinja2/scaffolds/jinja2_starter/+package+/views.py_tmpl
pyramid_jinja2/scaffolds/jinja2_starter/+package+/locale/+project+.pot
pyramid_jinja2/scaffolds/jinja2_starter/+package+/locale/de/LC_MESSAGES/+project+.mo
pyramid_jinja2/scaffolds/jinja2_starter/+package+/locale/de/LC_MESSAGES/+project+.po
pyramid_jinja2/scaffolds/jinja2_starter/+package+/locale/fr/LC_MESSAGES/+project+.mo
pyramid_jinja2/scaffolds/jinja2_starter/+package+/locale/fr/LC_MESSAGES/+project+.po
pyramid_jinja2/scaffolds/jinja2_starter/+package+/static/favicon.ico
pyramid_jinja2/scaffolds/jinja2_starter/+package+/static/pyramid-16x16.png
pyramid_jinja2/scaffolds/jinja2_starter/+package+/static/pyramid.png
pyramid_jinja2/scaffolds/jinja2_starter/+package+/static/theme.css
pyramid_jinja2/scaffolds/jinja2_starter/+package+/templates/mytemplate.jinja2_tmpl
pyramid_jinja2-2.10.dist-info/LICENSE.txt
pyramid_jinja2-2.10.dist-info/METADATA
pyramid_jinja2-2.10.dist-info/WHEEL
pyramid_jinja2-2.10.dist-info/entry_points.txt
pyramid_jinja2-2.10.dist-info/top_level.txt
pyramid_jinja2-2.10.dist-info/RECORD
