Metadata-Version: 2.1
Name: pyramid-jinja2
Version: 2.10
Summary: Jinja2 template bindings for the Pyramid web framework
Home-page: https://github.com/Pylons/pyramid_jinja2
Author: Rocky Burt
Author-email: pylons-discuss@googlegroups.com
Maintainer: Pylons Project
Maintainer-email: pylons-discuss@googlegroups.com
License: BSD-derived (Repoze)
Project-URL: Documentation, https://docs.pylonsproject.org/projects/pyramid_jinja2/en/latest/
Project-URL: Changelog, https://github.com/Pylons/pyramid_jinja2/blob/master/CHANGES.rst
Project-URL: Issue Tracker, https://github.com/Pylons/pyramid_jinja2/issues
Keywords: web wsgi pylons pyramid jinja2
Platform: UNKNOWN
Classifier: Development Status :: 6 - Mature
Classifier: Intended Audience :: Developers
Classifier: Programming Language :: Python
Classifier: Programming Language :: Python :: 3
Classifier: Programming Language :: Python :: 3.7
Classifier: Programming Language :: Python :: 3.8
Classifier: Programming Language :: Python :: 3.9
Classifier: Programming Language :: Python :: 3.10
Classifier: Framework :: Pyramid
Classifier: License :: Repoze Public License
Requires-Python: >=3.7.0
Provides-Extra: testing
Provides-Extra: docs
License-File: LICENSE.txt
